plotsurfacetool/FunctionEvaluationHelper.py
plotsurfacetool/OutputStatistic.py
plotsurfacetool/PlotSettings.py
plotsurfacetool/PlotSurfaceTool.py
plotsurfacetool/__init__.py
plotsurfacetool-0.1.0.dist-info/METADATA
plotsurfacetool-0.1.0.dist-info/WHEEL
plotsurfacetool-0.1.0.dist-info/top_level.txt
plotsurfacetool-0.1.0.dist-info/RECORD
