Metadata-Version: 2.1
Name: plotsurfacetool
Version: 0.1.0
Summary: A package for evaluating and plotting functions.
Home-page: https://github.com/da-roth/StableAndBiasFreeMonteCarloGreeks/src/PlotSurfaceTool
Author: Daniel Roth
Author-email: danielroth@posteo.eu
Classifier: Programming Language :: Python :: 3
Classifier: License :: OSI Approved :: MIT License
Classifier: Operating System :: OS Independent
Requires-Python: >=3.6
Requires-Dist: numpy
Requires-Dist: matplotlib
